cifti/__init__.py
cifti/axis.py
cifti/io.py
cifti/tests/__init__.py
cifti/tests/test_axis.py
cifti/tests/test_io.py
cifti/tests/test_name.py
cifti-1.1.dist-info/DESCRIPTION.rst
cifti-1.1.dist-info/METADATA
cifti-1.1.dist-info/RECORD
cifti-1.1.dist-info/WHEEL
cifti-1.1.dist-info/metadata.json
cifti-1.1.dist-info/pbr.json
cifti-1.1.dist-info/top_level.txt
