Metadata-Version: 2.0
Name: cifti
Version: 1.1
Summary: Interface to handle CIFTI files
Home-page: https://git.fmrib.ox.ac.uk/ndcn0236/cifti
Author: Michiel Cottaar
Author-email: Michiel.Cottaar@ndcn.ox.ac.uk
License: MIT
Platform: UNKNOWN
Requires-Dist: numpy
Requires-Dist: nibabel (>=2.2)
Requires-Dist: six
